qaviton_git/__init__.py
qaviton_git/git_wrapper.py
qaviton_git/logger.py
qaviton_git-2019.9.29.11.11.3.489379.dist-info/LICENSE
qaviton_git-2019.9.29.11.11.3.489379.dist-info/METADATA
qaviton_git-2019.9.29.11.11.3.489379.dist-info/WHEEL
qaviton_git-2019.9.29.11.11.3.489379.dist-info/top_level.txt
qaviton_git-2019.9.29.11.11.3.489379.dist-info/RECORD
