Metadata-Version: 2.1
Name: qaviton-git
Version: 2019.9.29.11.11.3.489379
Summary: qaviton git
Home-page: https://github.com/qaviton/qaviton_git.git
Author: yehonadav
Author-email: yonadav.barilan@gmail.com
License: apache-2.0
Platform: UNKNOWN
Classifier: Programming Language :: Python :: 3.6
Requires-Dist: qaviton-helpers (>=2019.9.4.11.27.8.183362)
Requires-Dist: qaviton-processes (>=2019.9.4.12.58.22.283354)
Requires-Dist: qaviton-handlers (>=2019.9.29.7.56.30.312631)
